CHANGELOG.md
pytest_antilru/__init__.py
pytest_antilru/main.py
pytest_antilru-2.0.0.dist-info/LICENSE
pytest_antilru-2.0.0.dist-info/METADATA
pytest_antilru-2.0.0.dist-info/WHEEL
pytest_antilru-2.0.0.dist-info/entry_points.txt
pytest_antilru-2.0.0.dist-info/RECORD
