Metadata-Version: 2.1
Name: pytest-antilru
Version: 2.0.0
Summary: Bust functools.lru_cache when running pytest to avoid test pollution
Home-page: https://github.com/ipwnponies/pytest-antilru
License: MIT
Author: John Nguyen
Author-email: ipwnponies@gmail.com
Requires-Python: >=3.8
Classifier: Development Status :: 5 - Production/Stable
Classifier: Framework :: Pytest
Classifier: License :: OSI Approved :: MIT License
Classifier: Programming Language :: Python :: 3
Classifier: Programming Language :: Python :: 3.8
Classifier: Programming Language :: Python :: 3.9
Classifier: Programming Language :: Python :: 3.10
Classifier: Programming Language :: Python :: 3.11
Classifier: Programming Language :: Python :: 3.12
Requires-Dist: pytest (>=7) ; python_version >= "3.10"
Project-URL: Repository, https://github.com/ipwnponies/pytest-antilru
